alpaca_isp/__init__.py
alpaca_isp/__main__.py
alpaca_isp/chips.py
alpaca_isp/exceptions.py
alpaca_isp/lpc.py
alpaca_isp-0.2.0.dist-info/DESCRIPTION.rst
alpaca_isp-0.2.0.dist-info/METADATA
alpaca_isp-0.2.0.dist-info/RECORD
alpaca_isp-0.2.0.dist-info/WHEEL
alpaca_isp-0.2.0.dist-info/entry_points.txt
alpaca_isp-0.2.0.dist-info/metadata.json
alpaca_isp-0.2.0.dist-info/top_level.txt
