Metadata-Version: 2.0
Name: alpaca-isp
Version: 0.2.0
Summary: In-system programming tool for LPC microcontrollers
Home-page: https://git.clayhobbs.com/clay/alpaca_isp
Author: Clayton G. Hobbs
Author-email: clay@lakeserv.net
License: Apache
Keywords: lpc microcontroller mcu flash isp
Platform: UNKNOWN
Classifier: Development Status :: 3 - Alpha
Classifier: Environment :: Console
Classifier: Intended Audience :: Developers
Classifier: License :: OSI Approved :: Apache Software License
Classifier: Operating System :: MacOS :: MacOS X
Classifier: Operating System :: Microsoft :: Windows
Classifier: Operating System :: POSIX
Classifier: Programming Language :: Python :: 3 :: Only
Classifier: Programming Language :: Python :: 3.6
Classifier: Topic :: Software Development :: Embedded Systems
Requires-Dist: IntelHex (>=2.1)
Requires-Dist: pyserial (>=3.4)
